Workbook
Name NativeTimeline_Date: #N/A
Name Slicer_Months__Date: #N/A
Name Slicer_Product: #N/A
Name Slicer_Region: #N/A

Sheet Sales data
A1: Order_ID | B1: Date | C1: Region | D1: Salesperson | E1: Product | F1: Category | G1: Units | H1: Unit_Price | I1: Cost
A2: 1001 | B2: 45658 | C2: North | D2: John | E2: Laptop | F2: Electronics | G2: 5 | H2: 800 | I2: 3000
A3: 1002 | B3: 45659 | C3: South | D3: Sarah | E3: Mobile | F3: Electronics | G3: 8 | H3: 500 | I3: 3100
A4: 1003 | B4: 45660 | C4: East | D4: David | E4: Printer | F4: Office Supplies | G4: 6 | H4: 150 | I4: 650
A5: 1004 | B5: 45661 | C5: West | D5: Emily | E5: Desk Chair | F5: Furniture | G5: 10 | H5: 120 | I5: 850
A6: 1005 | B6: 45662 | C6: North | D6: John | E6: Tablet | F6: Electronics | G6: 7 | H6: 400 | I6: 2100
A7: 1006 | B7: 45663 | C7: South | D7: Sarah | E7: Monitor | F7: Electronics | G7: 9 | H7: 250 | I7: 1700
A8: 1007 | B8: 45664 | C8: East | D8: David | E8: Keyboard | F8: Office Supplies | G8: 15 | H8: 40 | I8: 420
A9: 1008 | B9: 45665 | C9: West | D9: Emily | E9: Office Desk | F9: Furniture | G9: 3 | H9: 600 | I9: 1300
A10: 1009 | B10: 45666 | C10: North | D10: John | E10: Headphones | F10: Electronics | G10: 12 | H10: 80 | I10: 700
A11: 1010 | B11: 45667 | C11: South | D11: Sarah | E11: Bookshelf | F11: Furniture | G11: 4 | H11: 200 | I11: 600
A12: 1011 | B12: 45668 | C12: East | D12: David | E12: Scanner | F12: Office Supplies | G12: 5 | H12: 300 | I12: 1100
A13: 1012 | B13: 45669 | C13: West | D13: Emily | E13: Smartwatch | F13: Electronics | G13: 6 | H13: 220 | I13: 950
... A81: 1080 | B81: 45737 | C81: West | D81: Emily | E81: Bookshelf | F81: Furniture | G81: 5 | H81: 250 | I81: 950

Sheet pivottable analysis
A1: Region | B1: Sum of Revenue | D1: Product | E1: Sum of Revenue
A2: East | B2: 17615 | D2: AC | E2: 8200
A3: West | B3: 27440 | D3: Camera | E3: 8450
A4: North | B4: 36665 | D4: Laptop | E4: 10100
A5: South | B5: 46210 | D5: Mobile | E5: 8950
D6: Tablet | E6: 10040
D7: Grand Total | E7: 45740
A9: Month | B9: Sum of Revenue | D9: Category | E9: Sum of Units
A10: 2025 | B10: 127930 | D10: Electronics | E10: 313
A11: Jan | B11: 48360 | D11: Furniture | E11: 141
A12: Feb | B12: 43380 | D12: Office Supplies | E12: 322
A13: Mar | B13: 36190 | D13: Grand Total | E13: 776
A14: Grand Total | B14: 127930
A16: Category | B16: Sum of profit | D16: Salesperson | E16: Sum of Revenue | F16: Sum of profit
A17: Electronics | B17: 19545 | D17: David | E17: 17615 | F17: 4555
A18: Furniture | B18: 8730 | D18: Emily | E18: 27440 | F18: 7060
A19: Office Supplies | B19: 2945 | D19: John | E19: 36665 | F19: 8815
A20: Grand Total | B20: 31220 | D20: Sarah | E20: 46210 | F20: 10790
D21: Grand Total | E21: 127930 | F21: 31220

Sheet Data
A1: Order_ID | B1: Date | C1: Region | D1: Salesperson | E1: Product | F1: Category | G1: Units | H1: Unit_Price | I1: Cost | J1: Revenue | K1: profit | L1: Month helper col
A2: 1001 | B2: 45658 | C2: North | D2: John | E2: Laptop | F2: Electronics | G2: 5 | H2: 800 | I2: 3000 | J2: =G2*H2 -> 4000 | K2: =J2-I2 -> 1000 | L2: =TEXT(B2,"mmm") -> Jan
A3: 1002 | B3: 45659 | C3: South | D3: Sarah | E3: Mobile | F3: Electronics | G3: 8 | H3: 500 | I3: 3100 | J3: =G3*H3 -> 4000 | K3: =J3-I3 -> 900 | L3: =TEXT(B3,"mmm") -> Jan
A4: 1003 | B4: 45660 | C4: East | D4: David | E4: Printer | F4: Office Supplies | G4: 6 | H4: 150 | I4: 650 | J4: =G4*H4 -> 900 | K4: =J4-I4 -> 250 | L4: =TEXT(B4,"mmm") -> Jan
A5: 1004 | B5: 45661 | C5: West | D5: Emily | E5: Desk Chair | F5: Furniture | G5: 10 | H5: 120 | I5: 850 | J5: =G5*H5 -> 1200 | K5: =J5-I5 -> 350 | L5: =TEXT(B5,"mmm") -> Jan
A6: 1005 | B6: 45662 | C6: North | D6: John | E6: Tablet | F6: Electronics | G6: 7 | H6: 400 | I6: 2100 | J6: =G6*H6 -> 2800 | K6: =J6-I6 -> 700 | L6: =TEXT(B6,"mmm") -> Jan
A7: 1006 | B7: 45663 | C7: South | D7: Sarah | E7: Monitor | F7: Electronics | G7: 9 | H7: 250 | I7: 1700 | J7: =G7*H7 -> 2250 | K7: =J7-I7 -> 550 | L7: =TEXT(B7,"mmm") -> Jan
A8: 1007 | B8: 45664 | C8: East | D8: David | E8: Keyboard | F8: Office Supplies | G8: 15 | H8: 40 | I8: 420 | J8: =G8*H8 -> 600 | K8: =J8-I8 -> 180 | L8: =TEXT(B8,"mmm") -> Jan
A9: 1008 | B9: 45665 | C9: West | D9: Emily | E9: Office Desk | F9: Furniture | G9: 3 | H9: 600 | I9: 1300 | J9: =G9*H9 -> 1800 | K9: =J9-I9 -> 500 | L9: =TEXT(B9,"mmm") -> Jan
A10: 1009 | B10: 45666 | C10: North | D10: John | E10: Headphones | F10: Electronics | G10: 12 | H10: 80 | I10: 700 | J10: =G10*H10 -> 960 | K10: =J10-I10 -> 260 | L10: =TEXT(B10,"mmm") -> Jan
A11: 1010 | B11: 45667 | C11: South | D11: Sarah | E11: Bookshelf | F11: Furniture | G11: 4 | H11: 200 | I11: 600 | J11: =G11*H11 -> 800 | K11: =J11-I11 -> 200 | L11: =TEXT(B11,"mmm") -> Jan
A12: 1011 | B12: 45668 | C12: East | D12: David | E12: Scanner | F12: Office Supplies | G12: 5 | H12: 300 | I12: 1100 | J12: =G12*H12 -> 1500 | K12: =J12-I12 -> 400 | L12: =TEXT(B12,"mmm") -> Jan
A13: 1012 | B13: 45669 | C13: West | D13: Emily | E13: Smartwatch | F13: Electronics | G13: 6 | H13: 220 | I13: 950 | J13: =G13*H13 -> 1320 | K13: =J13-I13 -> 370 | L13: =TEXT(B13,"mmm") -> Jan
... A81: 1080 | B81: 45737 | C81: West | D81: Emily | E81: Bookshelf | F81: Furniture | G81: 5 | H81: 250 | I81: 950 | J81: =G81*H81 -> 1250 | K81: =J81-I81 -> 300 | L81: =TEXT(B81,"mmm") -> Mar

Sheet Summary
B1: Total Revenue | C1: Total profit | D1: profit marigin % | E1: Unit total sold | F1: Revenue by region | G1: Dynamic region | I1: Unique products | J1: Total revenue
B2: =SUM(Data!J2:J81) -> 127930 | C2: =SUM(Data!K2:K81) -> 31220 | D2: =SUM(Data!K2:K81)/SUM(Data!I2:I81) -> 0.3228208 | E2: =SUM(Data!G2:G81) -> 776 | F2: =SUMIFS(Data!J:J, Data!C:C, "North") -> 36665 | G2: =SUMIFS(Data!J:J, Data!C:C, C5) -> 36665 | I2: {=_xlfn.UNIQUE(Data!E2:E81)} -> Laptop | J2: =SUMIFS(Data!J2:J81, Data!E2:E81, I2) -> 10100
I3: Mobile | J3: =SUMIFS(Data!J3:J82, Data!E3:E82, I3) -> 8950
B4: Unique region | I4: Printer | J4: =SUMIFS(Data!J4:J83, Data!E4:E83, I4) -> 2600
B5: {=_xlfn.UNIQUE(Data!C2:C81)} -> North | C5: North | D5: max sales | F5: Best spelling product | I5: Desk Chair | J5: =SUMIFS(Data!J5:J84, Data!E5:E84, I5) -> 2320
B6: South | D6: =MAX(J2:J35) -> 10100 | F6: {=_xlfn.XLOOKUP(D6,J2:J35,I2:J35)} -> Laptop | G6: 10100 | I6: Tablet | J6: =SUMIFS(Data!J6:J85, Data!E6:E85, I6) -> 10040
B7: East | I7: Monitor | J7: =SUMIFS(Data!J7:J86, Data!E7:E86, I7) -> 5430
B8: West | I8: Keyboard | J8: =SUMIFS(Data!J8:J87, Data!E8:E87, I8) -> 1370
D9: month helper | E9: Monthly revenue | F9: month growth % | I9: Office Desk | J9: =SUMIFS(Data!J9:J88, Data!E9:E88, I9) -> 1800
D10: {=_xlfn.UNIQUE(Data!L2:L81)} -> Jan | E10: =SUMIFS(Data!I:I, Data!L:L, D10) -> 36250 | F10: =(E10-E11)/E10 -> 0.092413793 | I10: Headphones | J10: =SUMIFS(Data!J10:J89, Data!E10:E89, I10) -> 960
D11: Feb | E11: =SUMIFS(Data!I:I, Data!L:L, D11) -> 32900 | F11: =(E11-E12)/E11 -> 0.16231003 | I11: Bookshelf | J11: =SUMIFS(Data!J11:J90, Data!E11:E90, I11) -> 3430
D12: Mar | E12: =SUMIFS(Data!I:I, Data!L:L, D12) -> 27560 | F12: =(E12-C14)/E12 -> 1 | I12: Scanner | J12: =SUMIFS(Data!J12:J91, Data!E12:E91, I12) -> 1500
I13: Smartwatch | J13: =SUMIFS(Data!J13:J92, Data!E13:E92, I13) -> 2790
I14: Router | J14: =SUMIFS(Data!J14:J93, Data!E14:E93, I14) -> 3345
I15: Cabinet | J15: =SUMIFS(Data!J15:J94, Data!E15:E94, I15) -> 4950
I16: Sofa | J16: =SUMIFS(Data!J16:J95, Data!E16:E95, I16) -> 6500
I17: Lamp | J17: =SUMIFS(Data!J17:J96, Data!E17:E96, I17) -> 2830
I18: Mouse | J18: =SUMIFS(Data!J18:J97, Data!E18:E97, I18) -> 1660
I19: Projector | J19: =SUMIFS(Data!J19:J98, Data!E19:E98, I19) -> 3600
I20: Notebook | J20: =SUMIFS(Data!J20:J99, Data!E20:E99, I20) -> 885
I21: Cupboard | J21: =SUMIFS(Data!J21:J100, Data!E21:E100, I21) -> 1500
I22: Camera | J22: =SUMIFS(Data!J22:J101, Data!E22:E101, I22) -> 8450
I23: Fan | J23: =SUMIFS(Data!J23:J102, Data!E23:E102, I23) -> 2700
I24: Stapler | J24: =SUMIFS(Data!J24:J103, Data!E24:E103, I24) -> 930
... I35: Desk | J35: =SUMIFS(Data!J35:J114, Data!E35:E114, I35) -> 3350

Sheet dashboard
A1: Sales Dashboard
